kde_diffusion/__init__.py
kde_diffusion/kde1d.py
kde_diffusion/kde2d.py
kde_diffusion/meta.py
kde_diffusion-1.0.5.dist-info/licenses/license.txt
kde_diffusion-1.0.5.dist-info/WHEEL
kde_diffusion-1.0.5.dist-info/METADATA
kde_diffusion-1.0.5.dist-info/RECORD
