Metadata-Version: 2.4
Name: KDE-diffusion
Version: 1.0.5
Summary: Kernel density estimation via diffusion in 1d and 2d
Keywords: kernel density estimation,statistics
Author: John Hennig
Requires-Python: >= 3.6
License-Expression: MIT
Classifier: Development Status :: 5 - Production/Stable
Classifier: Programming Language :: Python :: 3
Classifier: Operating System :: OS Independent
Classifier: Topic :: Scientific/Engineering :: Information Analysis
Classifier: Intended Audience :: Science/Research
License-File: license.txt
Requires-Dist: NumPy
Requires-Dist: SciPy
Requires-Dist: Sphinx ; extra == "docs"
Requires-Dist: Furo ; extra == "docs"
Requires-Dist: MyST-parser ; extra == "docs"
Requires-Dist: CommonMark ; extra == "docs"
Project-URL: Documentation, https://kde-diffusion.readthedocs.io
Project-URL: Source, https://github.com/john-hen/kde-diffusion
Provides-Extra: docs
